mlx/__main__.py
mlx/_reprlib_fix.py
mlx/distributed_run.py
mlx/extension.py
mlx/py.typed
mlx/utils.py
mlx/include/mlx/allocator.h
mlx/include/mlx/array.h
mlx/include/mlx/compile.h
mlx/include/mlx/compile_impl.h
mlx/include/mlx/device.h
mlx/include/mlx/dtype.h
mlx/include/mlx/dtype_utils.h
mlx/include/mlx/einsum.h
mlx/include/mlx/event.h
mlx/include/mlx/export.h
mlx/include/mlx/export_impl.h
mlx/include/mlx/fast.h
mlx/include/mlx/fast_primitives.h
mlx/include/mlx/fence.h
mlx/include/mlx/fft.h
mlx/include/mlx/graph_utils.h
mlx/include/mlx/io.h
mlx/include/mlx/linalg.h
mlx/include/mlx/memory.h
mlx/include/mlx/mlx.h
mlx/include/mlx/ops.h
mlx/include/mlx/primitives.h
mlx/include/mlx/random.h
mlx/include/mlx/scheduler.h
mlx/include/mlx/small_vector.h
mlx/include/mlx/stream.h
mlx/include/mlx/threadpool.h
mlx/include/mlx/transforms.h
mlx/include/mlx/transforms_impl.h
mlx/include/mlx/utils.h
mlx/include/mlx/version.h
mlx/include/mlx/3rdparty/pocketfft.h
mlx/include/mlx/backend/common/binary.h
mlx/include/mlx/backend/common/broadcasting.h
mlx/include/mlx/backend/common/buffer_cache.h
mlx/include/mlx/backend/common/compiled.h
mlx/include/mlx/backend/common/copy.h
mlx/include/mlx/backend/common/hadamard.h
mlx/include/mlx/backend/common/matmul.h
mlx/include/mlx/backend/common/reduce.h
mlx/include/mlx/backend/common/slicing.h
mlx/include/mlx/backend/common/ternary.h
mlx/include/mlx/backend/common/unary.h
mlx/include/mlx/backend/common/utils.h
mlx/include/mlx/backend/cpu/arange.h
mlx/include/mlx/backend/cpu/available.h
mlx/include/mlx/backend/cpu/binary.h
mlx/include/mlx/backend/cpu/binary_ops.h
mlx/include/mlx/backend/cpu/binary_two.h
mlx/include/mlx/backend/cpu/compiled_preamble.h
mlx/include/mlx/backend/cpu/copy.h
mlx/include/mlx/backend/cpu/encoder.h
mlx/include/mlx/backend/cpu/eval.h
mlx/include/mlx/backend/cpu/gemm.h
mlx/include/mlx/backend/cpu/jit_compiler.h
mlx/include/mlx/backend/cpu/lapack.h
mlx_cpu-0.29.4.dist-info/METADATA
mlx_cpu-0.29.4.dist-info/WHEEL
mlx_cpu-0.29.4.dist-info/top_level.txt
mlx_cpu-0.29.4.dist-info/RECORD
mlx_cpu-0.29.4.dist-info/licenses/LICENSE
mlx_cpu-0.29.4.dist-info/sboms/auditwheel.cdx.json
