Metadata-Version: 2.4
Name: mlx-cpu
Version: 0.29.4
Summary: A framework for machine learning on Apple silicon.
Home-page: https://github.com/ml-explore/mlx
Author: MLX Contributors
Author-email: mlx@group.apple.com
License: MIT
Requires-Python: >=3.10
License-File: LICENSE
Dynamic: author
Dynamic: author-email
Dynamic: description
Dynamic: description-content-type
Dynamic: home-page
Dynamic: license
Dynamic: license-file
Dynamic: requires-python
Dynamic: summary
